{"name":"Custom","methods":{"GetLUT":{"usage":["float64 :GetLUT(int inp, float64 v)"]},"info_text":"Discovered methods might be available in many contexts, but most typically in Fuse scripts","GetNum":{"usage":["float64 :GetNum(int inp, float64 time)"]},"GetPtY":{"usage":["float64 :GetPtY(int inp, float64 time)"]},"GetPtX":{"usage":["float64 :GetPtX(int inp, float64 time)"]},"header_text":"Discovered Methods"},"attributes":{"REGB_NoMotionBlurCtrls":{"type":"false","value":"boolean"},"REGS_OpIconString":{"type":"CT","value":"string"},"REGS_OpDescription":{"type":"Custom Tool","value":"string"},"REGS_Name":{"type":"Custom Tool","value":"string"},"REGB_ControlView":{"type":"false","value":"boolean"},"REGS_Category":{"type":"Miscellaneous","value":"string"},"REGI_ClassType":{"type":"3 = CT_Tool","value":"number (integer)"},"REGB_Unpredictable":{"type":"false","value":"boolean"},"REGS_VersionString":{"type":"Built: Jul 19 2023","value":"string"},"REGB_ForceCommonCtrls":{"type":"false","value":"boolean"},"REGS_UIName":{"type":"Custom Tool","value":"string"},"REGI_OpIcon":{"type":"0","value":"number (integer)"},"REGS_IconID":{"type":"Icons.Tools.Icons.CustomTool","value":"string"},"REGB_Source_GlobalCtrls":{"type":"false","value":"boolean"},"REGB_OpNoMask":{"type":"false","value":"boolean"},"REGB_Source_SizeCtrls":{"type":"false","value":"boolean"},"REGB_Hide":{"type":"false","value":"boolean"},"REGB_Source_AspectCtrls":{"type":"false","value":"boolean"},"REGS_ID":{"type":"Custom","value":"string"},"REGB_NoAutoProxy":{"type":"false","value":"boolean"},"REGS_HelpTopic":{"type":"Tools/Miscellaneous/Custom","value":"string"},"REGS_FileName":{"type":"C:\\Program Files\\Blackmagic Design\\Fusion 18\\fusionoperators.dll","value":"string"},"REGI_Version":{"type":"0","value":"number (integer)"},"REGI_Priority":{"type":"0","value":"number (integer)"},"REGB_OperatorControl":{"type":"false","value":"boolean"},"REGB_NoBlendCtrls":{"type":"false","value":"boolean"},"REGB_SupportsDoD":{"type":"true","value":"boolean"},"REGB_NoObjMatCtrls":{"type":"false","value":"boolean"}},"class_inheritance":["Object","Operator","ThreadedOperator"]}