{
    "attributes": {
        "REGS_FileName": {
            "type": "C:\\Program Files\\Blackmagic Design\\Fusion 18\\fusionoperators.dll",
            "value": "string"
        },
        "REGS_VersionString": {
            "type": "Built: May 20 2023",
            "value": "string"
        },
        "REGB_ControlView": {
            "type": "false",
            "value": "boolean"
        },
        "REGS_Category": {
            "type": "Mask",
            "value": "string"
        },
        "REGI_ClassType": {
            "type": "35 = CT_Mask",
            "value": "number (integer)"
        },
        "REGB_Unpredictable": {
            "type": "false",
            "value": "boolean"
        },
        "REGB_ForceCommonCtrls": {
            "type": "false",
            "value": "boolean"
        },
        "REGI_OpIcon": {
            "type": "0",
            "value": "number (integer)"
        },
        "REGB_OperatorControl": {
            "type": "false",
            "value": "boolean"
        },
        "REGI_Version": {
            "type": "0",
            "value": "number (integer)"
        },
        "REGB_Source_GlobalCtrls": {
            "type": "false",
            "value": "boolean"
        },
        "REGB_OpNoMask": {
            "type": "false",
            "value": "boolean"
        },
        "REGB_Source_SizeCtrls": {
            "type": "false",
            "value": "boolean"
        },
        "REGI_DataType": {
            "type": "Mask",
            "value": "number (integer)"
        },
        "REGB_Source_AspectCtrls": {
            "type": "false",
            "value": "boolean"
        },
        "REGS_OpDescription": {
            "type": "Draw a Polyline",
            "value": "string"
        },
        "REGB_NoAutoProxy": {
            "type": "false",
            "value": "boolean"
        },
        "REGB_Hide": {
            "type": "false",
            "value": "boolean"
        },
        "REGB_SupportsDoD": {
            "type": "true",
            "value": "boolean"
        },
        "REGS_Name": {
            "type": "Polygon",
            "value": "string"
        },
        "REGI_Priority": {
            "type": "0",
            "value": "number (integer)"
        },
        "REGS_IconID": {
            "type": "Icons.Tools.Icons.PolygonMask",
            "value": "string"
        },
        "REGB_NoBlendCtrls": {
            "type": "false",
            "value": "boolean"
        },
        "REGS_ID": {
            "type": "PolylineMask",
            "value": "string"
        },
        "REGB_NoObjMatCtrls": {
            "type": "false",
            "value": "boolean"
        },
        "REGS_HelpTopic": {
            "type": "Tools/Masks/Polygon",
            "value": "string"
        },
        "REGB_NoMotionBlurCtrls": {
            "type": "false",
            "value": "boolean"
        },
        "REGS_OpIconString": {
            "type": "Ply",
            "value": "string"
        },
        "REGS_UIName": {
            "type": "Polygon",
            "value": "string"
        }
    },
    "name": "PolylineMask",
    "methods": {
        "ConvertToBezier": {
            "short_help": "Converts to Bezier polyline",
            "usage": [
                " :ConvertToBezier()"
            ]
        },
        "ConvertToBSpline": {
            "short_help": "Converts to b-spline polyline",
            "usage": [
                " :ConvertToBSpline()"
            ]
        },
        "GetBezierPolyline": {
            "short_help": "Get a table of bezier polyline",
            "description": "second argument:  Can be 'outter' in case of retrieving outter polyline (case sensitive)\nReturns: table of Bezier polyline (converts to Bezier if necessary",
            "usage": [
                "table :GetBezierPolyline(number time, [string which])"
            ]
        }
    },
    "class_inheritance": [
        "Object",
        "Operator",
        "ThreadedOperator",
        "MaskOperator"
    ]
}